mcpstore/__init__.py
mcpstore/adapters/__init__.py
mcpstore/adapters/autogen_adapter.py
mcpstore/adapters/common.py
mcpstore/adapters/crewai_adapter.py
mcpstore/adapters/langchain_adapter.py
mcpstore/adapters/langgraph_adapter.py
mcpstore/adapters/llamaindex_adapter.py
mcpstore/adapters/openai_adapter.py
mcpstore/adapters/semantic_kernel_adapter.py
mcpstore/api/__init__.py
mcpstore/cli/__init__.py
mcpstore/cli/config_manager.py
mcpstore/cli/main.py
mcpstore/cli/api/__init__.py
mcpstore/cli/api/run.py
mcpstore/cli/config/__init__.py
mcpstore/cli/config/commands.py
mcpstore/cli/mcp/__init__.py
mcpstore/cli/mcp/commands.py
mcpstore/config/__init__.py
mcpstore/config/cache_config.py
mcpstore/config/cache_environment.py
mcpstore/config/config.py
mcpstore/config/config_dataclasses.py
mcpstore/config/config_defaults.py
mcpstore/config/health_check.py
mcpstore/config/json_config.py
mcpstore/config/path_utils.py
mcpstore/config/redis_errors.py
mcpstore/config/toml_config.py
mcpstore/core/__init__.py
mcpstore/core/exceptions.py
mcpstore/core/orchestrator.py
mcpstore/core/agents/__init__.py
mcpstore/core/agents/session_manager.py
mcpstore/core/application/__init__.py
mcpstore/core/application/service_application_service.py
mcpstore/core/architecture/__init__.py
mcpstore/core/architecture/service_management_core.py
mcpstore/core/architecture/service_management_shells.py
mcpstore/core/architecture/show_config_core.py
mcpstore/core/architecture/show_config_shell.py
mcpstore/core/bridge/__init__.py
mcpstore/core/bridge/async_orchestrated_bridge.py
mcpstore/core/cache/__init__.py
mcpstore/core/cache/cache_layer_manager.py
mcpstore/core/cache/models.py
mcpstore/core/cache/naming_service.py
mcpstore/core/cache/relationship_manager.py
mcpstore/core/cache/service_entity_manager.py
mcpstore/core/cache/state_manager.py
mcpstore/core/cache/tool_entity_manager.py
mcpstore/core/configuration/__init__.py
mcpstore/core/configuration/config_export_service.py
mcpstore-1.5.14.dist-info/licenses/LICENSE
mcpstore-1.5.14.dist-info/METADATA
mcpstore-1.5.14.dist-info/WHEEL
mcpstore-1.5.14.dist-info/entry_points.txt
mcpstore-1.5.14.dist-info/top_level.txt
mcpstore-1.5.14.dist-info/RECORD
