Metadata-Version: 2.4
Name: mcpstore
Version: 1.5.14
Summary: A composable, ready-to-use MCP toolkit for agents and rapid integration.
Author-email: ooooofish <ooooofish@126.com>
License-Expression: MIT
Project-URL: Homepage, https://github.com/whillhill/mcpstore
Project-URL: Bug Tracker, https://github.com/whillhill/mcpstore/issues
Classifier: Programming Language :: Python :: 3
Classifier: Programming Language :: Python :: 3.10
Classifier: Programming Language :: Python :: 3.11
Classifier: Programming Language :: Python :: 3.12
Classifier: Programming Language :: Python :: 3.13
Classifier: Operating System :: OS Independent
Requires-Python: >=3.10
License-File: LICENSE
Requires-Dist: fastapi>=0.115.12
Requires-Dist: fastmcp>=2.7.1
Requires-Dist: httpx>=0.28.1
Requires-Dist: pydantic>=2.11.5
Requires-Dist: uvicorn>=0.30.0
Requires-Dist: typer>=0.9.0
Requires-Dist: py-key-value-aio>=0.1.0
Requires-Dist: toml>=0.10.2
Dynamic: license-file
